Metadata-Version: 1.1
Name: canaria-domestica-red-black
Version: 1.0.1
Summary: A simple package that works in some versions and is broken in others
Home-page: https://github.com/apljungquist/tox-constraints
Author: AP Ljungquist
Author-email: ap@ljungquist.eu
License: MIT
Platform: UNKNOWN
Classifier: License :: OSI Approved :: MIT License
